happy_config/__init__.py
happy_config/__main__.py
happy_config/config_loader.py
happy_config/cli/__init__.py
happy_config/cli/app.py
happy_config/cli/search_space.py
happy_config/param_tuning/__init__.py
happy_config/param_tuning/search_space.py
happy_config/typechecking/__init__.py
happy_config/typechecking/typecheck.py
happy_config/typechecking/typecheck_error.py
happy_config/typechecking/types.py
happy_config/typechecking/utils.py
happy_config-0.0.4.dist-info/LICENSE
happy_config-0.0.4.dist-info/METADATA
happy_config-0.0.4.dist-info/WHEEL
happy_config-0.0.4.dist-info/top_level.txt
happy_config-0.0.4.dist-info/RECORD
