Metadata-Version: 2.1
Name: happy-config
Version: 0.0.4
Summary: Managing ML experiment configuation with joy.
Home-page: https://github.com/GraphCL/happy_config
Author: Yichen Xu
Author-email: yichen.x@outlook.com
License: UNKNOWN
Platform: UNKNOWN
Classifier: Programming Language :: Python :: 3
Classifier: License :: OSI Approved :: MIT License
Classifier: Operating System :: OS Independent
Requires-Python: >=3.7
Requires-Dist: pyyaml
Requires-Dist: nni
